GatewayService/__init__.py
GatewayService/__main__.py
GatewayService/collection.py
GatewayService/const.py
GatewayService/service.py
pih_gateway-0.13.dist-info/METADATA
pih_gateway-0.13.dist-info/WHEEL
pih_gateway-0.13.dist-info/entry_points.txt
pih_gateway-0.13.dist-info/top_level.txt
pih_gateway-0.13.dist-info/RECORD
