Metadata-Version: 2.1
Name: pih-gateway
Version: 0.13
Summary: PIH Whatsapp message and Alisa command gateway service package
Home-page: https://pacifichosp.com/
Author: Nikita Karachentsev
Author-email: it@pacifichosp.com
License: MIT
Requires-Dist: ipih
Requires-Dist: fastapi
Requires-Dist: uvicorn
